{
	"type": "minecraft:crafting_shapeless",
	"ingredients":
	[
		{ "item": "hexcraft:glowing_hexorium_glass_skyblue" },
		{ "item": "hexcraft:glowing_hexorium_glass_skyblue" },
		{ "item": "hexcraft:glowing_hexorium_glass_skyblue" },
		{ "item": "hexcraft:glowing_hexorium_glass_skyblue" },
		{ "item": "hexcraft:glowing_hexorium_glass_skyblue" },
		{ "item": "hexcraft:glowing_hexorium_glass_skyblue" },
		{ "item": "hexcraft:glowing_hexorium_glass_skyblue" },
		{ "item": "hexcraft:glowing_hexorium_glass_skyblue" }
	],
	"result": { "item": "hexcraft:energized_hexorium_skyblue" }
}