{
	"type": "minecraft:crafting_shapeless",
	"ingredients":
	[
		{ "item": "hexcraft:glowing_hexorium_glass_gray" },
		{ "item": "hexcraft:glowing_hexorium_glass_gray" },
		{ "item": "hexcraft:glowing_hexorium_glass_gray" },
		{ "item": "hexcraft:glowing_hexorium_glass_gray" },
		{ "item": "hexcraft:glowing_hexorium_glass_gray" },
		{ "item": "hexcraft:glowing_hexorium_glass_gray" },
		{ "item": "hexcraft:glowing_hexorium_glass_gray" },
		{ "item": "hexcraft:glowing_hexorium_glass_gray" }
	],
	"result": { "item": "hexcraft:energized_hexorium_gray" }
}